django_jwt_2fa/__init__.py
django_jwt_2fa/apps.py
django_jwt_2fa/constants.py
django_jwt_2fa/exceptions.py
django_jwt_2fa/models.py
django_jwt_2fa/permissions.py
django_jwt_2fa/serializers.py
django_jwt_2fa/services/__init__.py
django_jwt_2fa/services/email.py
django_jwt_2fa/services/otp.py
django_jwt_2fa/settings.py
django_jwt_2fa/tokens.py
django_jwt_2fa/urls.py
django_jwt_2fa/views.py
django_jwt_2fa-0.1.2.dist-info/METADATA
django_jwt_2fa-0.1.2.dist-info/WHEEL
django_jwt_2fa-0.1.2.dist-info/RECORD
