Metadata-Version: 2.4
Name: django-jwt-2fa
Version: 0.1.2
Summary: Role-aware JWT-based 2FA for DRF
Author: Anjaan Gaire
Author-email: anjaangaire@gmail.com
Requires-Python: >=3.12
Classifier: Programming Language :: Python :: 3
Classifier: Programming Language :: Python :: 3.12
Classifier: Programming Language :: Python :: 3.13
Classifier: Programming Language :: Python :: 3.14
